odoo/addons/storage_backend/README.rst
odoo/addons/storage_backend/__init__.py
odoo/addons/storage_backend/__manifest__.py
odoo/addons/storage_backend/components/__init__.py
odoo/addons/storage_backend/components/base_adapter.py
odoo/addons/storage_backend/components/filesystem_adapter.py
odoo/addons/storage_backend/data/data.xml
odoo/addons/storage_backend/i18n/es.po
odoo/addons/storage_backend/i18n/it.po
odoo/addons/storage_backend/i18n/storage_backend.pot
odoo/addons/storage_backend/models/__init__.py
odoo/addons/storage_backend/models/storage_backend.py
odoo/addons/storage_backend/readme/CONTRIBUTORS.md
odoo/addons/storage_backend/readme/CREDITS.md
odoo/addons/storage_backend/readme/DESCRIPTION.md
odoo/addons/storage_backend/readme/HISTORY.md
odoo/addons/storage_backend/readme/USAGE.md
odoo/addons/storage_backend/security/ir.model.access.csv
odoo/addons/storage_backend/static/description/icon.png
odoo/addons/storage_backend/static/description/index.html
odoo/addons/storage_backend/tests/__init__.py
odoo/addons/storage_backend/tests/common.py
odoo/addons/storage_backend/tests/test_filesystem.py
odoo/addons/storage_backend/views/backend_storage_view.xml
odoo_addon_storage_backend-18.0.1.0.0.6.dist-info/METADATA
odoo_addon_storage_backend-18.0.1.0.0.6.dist-info/WHEEL
odoo_addon_storage_backend-18.0.1.0.0.6.dist-info/top_level.txt
odoo_addon_storage_backend-18.0.1.0.0.6.dist-info/RECORD
